Workbook

Sheet 📘 Instruções
A1: PriceRadar
A3: PriceRadar — Inteligência Competitiva de Preços para SaaS
A5: 1. CONCORRENTES: Cadastre seus concorrentes diretos com preços atuais. Atualize a coluna 'Preço Atual' sempre que detectar mudanças e mova o valor antigo para 'Preço Anterior'. A variação é calculada automaticamente.
A7: 2. PLANOS: Mapeie todos os planos/tiers de cada concorrente. Registre preço mensal, anual, features e limitações. A coluna 'Posição vs Nosso Preço' compara automaticamente (ajuste os valores de referência nas fórmulas para refletir seu preço).
A9: 3. HISTÓRICO: Toda vez que um concorrente mudar preço, feature ou packaging, registre aqui com data. Isso cria sua timeline de inteligência competitiva. A coluna 'Mudança Recente?' marca automaticamente alterações dos últimos 30 dias.
A11: 4. DEALS: Registre deals perdidos, em risco ou ganhos onde concorrentes foram citados. Vincule ao concorrente para calcular automaticamente a diferença de preço. Use a coluna 'Aprendizado' para alimentar seu playbook de vendas.
A13: 5. DASHBOARD: Visão consolidada com métricas-chave. Atualiza automaticamente com dados das outras abas.
A15: Rotina sugerida: Verifique páginas de preço dos concorrentes semanalmente (segundas). Atualize a aba Concorrentes e registre mudanças no Histórico. Revise Deals perdidos por preço mensalmente para identificar padrões. Compartilhe o Dashboard com o time de vendas antes de reuniões de pipeline.

Sheet Dashboard
A1: Métrica | B1: Valor | C1: Variação | D1: Período | E1: Status
A2: Concorrentes monitorados | B2: =COUNTA(Concorrentes!A3:A20) | D2: Abr/2026 | E2: ✅
A3: Alterações de preço detectadas (mês) | B3: =COUNTIF(Histórico!H3:H100,"Sim") | C3: +2 | D3: Abr/2026 | E3: 🔴
A4: Maior aumento detectado | B4: +18% | D4: Abr/2026 | E4: ⚠️
A5: Maior redução detectada | B5: -12% | D5: Abr/2026 | E5: ⚠️
A6: Seu posicionamento médio vs mercado | B6: -7% | C6: +3pp | D6: Abr/2026 | E6: ✅
A7: Deals perdidos por preço (mês) | B7: =SUMPRODUCT((Deals!F3:F50="Preço")*(Deals!G3:G50)) | C7: +1 | D7: Abr/2026 | E7: 🔴
A8: Economia potencial c/ reposicionamento | B8: R$ 28.500 | D8: Abr/2026
A9: Última atualização de dados | B9: =COUNTA(Planos!A3:A50) | E9: ✅
A10: Planos concorrentes mapeados | B10: =ROUND(AVERAGE(Concorrentes!H3:H20),0) | C10: +3 | D10: Abr/2026
A11: Score competitividade (0-100) | B11: 72 | C11: +5 | D11: Abr/2026 | E11: ✅

Sheet Concorrentes
A1: Concorrente | B1: Website | C1: Segmento | D1: Plano Monitorado | E1: Preço Atual (R$/mês) | F1: Preço Anterior (R$/mês) | G1: Variação % | H1: Score Competitividade (0-100) | I1: Última Verificação | J1: Fonte do Dado | K1: Notas
A2: RivalCRM | B2: rivalcrm.com.br | C2: CRM | D2: Pro | E2: 299 | F2: 249 | H2: 68 | I2: 28/04/2026 | J2: Página de preços | K2: Subiu em março
A3: FlowDesk | B3: flowdesk.io | C3: Helpdesk | D3: Business | E3: 189 | F3: 189 | G3: =IF(F3=0,"N/A",ROUND((E3-F3)/F3*100,1)&"%") | H3: 75 | I3: 25/04/2026 | J3: Página de preços | K3: Estável há 6 meses
A4: MetricaPro | B4: metricapro.com | C4: Analytics | D4: Growth | E4: 449 | F4: 399 | G4: =IF(F4=0,"N/A",ROUND((E4-F4)/F4*100,1)&"%") | H4: 62 | I4: 27/04/2026 | J4: Proposta comercial | K4: Novo tier Enterprise
A5: ChatBot360 | B5: chatbot360.com | C5: Chatbot | D5: Scale | E5: 349 | F5: 349 | G5: =IF(F5=0,"N/A",ROUND((E5-F5)/F5*100,1)&"%") | H5: 80 | I5: 26/04/2026 | J5: Página de preços | K5: Adicionou add-on IA
A6: PipeRun | B6: piperun.com | C6: CRM | D6: Avançado | E6: 259 | F6: 279 | G6: =IF(F6=0,"N/A",ROUND((E6-F6)/F6*100,1)&"%") | H6: 71 | I6: 28/04/2026 | J6: Página de preços | K6: Reduziu para competir
A7: NexTask | B7: nextask.app | C7: Gestão | D7: Team | E7: 199 | F7: 179 | G7: =IF(F7=0,"N/A",ROUND((E7-F7)/F7*100,1)&"%") | H7: 65 | I7: 24/04/2026 | J7: Página de preços | K7: Aumento discreto
G8: =IF(F8=0,"N/A",ROUND((E8-F8)/F8*100,1)&"%")

Sheet Planos
A1: Concorrente | B1: Nome do Plano | C1: Preço Mensal (R$) | D1: Preço Anual (R$/mês) | E1: Desconto Anual % | F1: Usuários Inclusos | G1: Features-Chave | H1: Limitações | I1: Posição vs Nosso Preço
A2: RivalCRM | B2: Starter | C2: 99 | D2: 79 | F2: 3 | G2: CRM básico, 1 pipeline | H2: Sem automação
A3: RivalCRM | B3: Pro | C3: 299 | D3: 239 | E3: =IF(D3=0,"N/A",ROUND((1-D3/C3)*100,0)&"%") | F3: 10 | G3: Automação, relatórios, API | H3: Sem white-label | I3: =IF(C3=0,"N/A",IF(C3>250,"Acima",IF(C3<200,"Abaixo","Similar")))
A4: RivalCRM | B4: Enterprise | C4: 699 | D4: 559 | E4: =IF(D4=0,"N/A",ROUND((1-D4/C4)*100,0)&"%") | F4: Ilimitado | G4: Tudo + suporte dedicado | H4: Nenhuma | I4: =IF(C4=0,"N/A",IF(C4>250,"Acima",IF(C4<200,"Abaixo","Similar")))
A5: FlowDesk | B5: Free | C5: 0 | D5: 0 | E5: =IF(D5=0,"N/A",ROUND((1-D5/C5)*100,0)&"%") | F5: 1 | G5: Tickets básicos | H5: 100 tickets/mês | I5: =IF(C5=0,"N/A",IF(C5>250,"Acima",IF(C5<200,"Abaixo","Similar")))
A6: FlowDesk | B6: Business | C6: 189 | D6: 149 | E6: ="N/A" | F6: 5 | G6: SLA, automação, chat | H6: Sem base conhecimento | I6: ="Abaixo"
A7: FlowDesk | B7: Enterprise | C7: 489 | D7: 389 | E7: =IF(D7=0,"N/A",ROUND((1-D7/C7)*100,0)&"%") | F7: 20 | G7: Tudo + SAML + SLA custom | H7: Nenhuma | I7: =IF(C7=0,"N/A",IF(C7>250,"Acima",IF(C7<200,"Abaixo","Similar")))
A8: MetricaPro | B8: Starter | C8: 149 | D8: 119 | E8: =IF(D8=0,"N/A",ROUND((1-D8/C8)*100,0)&"%") | F8: 2 | G8: Dashboards, 3 integrações | H8: Dados 30 dias | I8: =IF(C8=0,"N/A",IF(C8>250,"Acima",IF(C8<200,"Abaixo","Similar")))
A9: MetricaPro | B9: Growth | C9: 449 | D9: 359 | E9: =IF(D9=0,"N/A",ROUND((1-D9/C9)*100,0)&"%") | F9: 10 | G9: Tudo + cohorts + export | H9: Sem API
A10: ChatBot360 | B10: Starter | C10: 129 | D10: 99 | E10: =IF(D10=0,"N/A",ROUND((1-D10/C10)*100,0)&"%") | F10: 1 | G10: 1 bot, 500 conversas/mês | H10: Sem IA
A11: ChatBot360 | B11: Scale | C11: 349 | D11: 279 | E11: =IF(D11=0,"N/A",ROUND((1-D11/C11)*100,0)&"%") | F11: 5 | G11: Bots ilimitados, IA, API | H11: 10k conversas/mês
A12: PipeRun | B12: Básico | C12: 99 | D12: 79 | E12: =IF(D12=0,"N/A",ROUND((1-D12/C12)*100,0)&"%") | F12: 3 | G12: Pipeline, propostas | H12: Sem relatórios
A13: PipeRun | B13: Avançado | C13: 259 | D13: 207 | E13: =IF(D13=0,"N/A",ROUND((1-D13/C13)*100,0)&"%") | F13: 10 | G13: Automação, relatórios, API | H13: Sem white-label
A14: NexTask | B14: Solo | C14: 49 | D14: 39 | E14: =IF(D14=0,"N/A",ROUND((1-D14/C14)*100,0)&"%") | F14: 1 | G14: Tarefas, Kanban | H14: 5 projetos
A15: NexTask | B15: Team | C15: 199 | D15: 159 | E15: =IF(D15=0,"N/A",ROUND((1-D15/C15)*100,0)&"%") | F15: 10 | G15: Tudo + Gantt + timesheet | H15: Sem custom fields
E16: =IF(D16=0,"N/A",ROUND((1-D16/C16)*100,0)&"%")

Sheet Histórico
A1: Data | B1: Concorrente | C1: Plano | D1: Campo Alterado | E1: Valor Anterior | F1: Valor Novo | G1: Variação % | H1: Mudança Recente? | I1: Impacto Estimado | J1: Ação Recomendada
A2: 01/03/2026 | B2: RivalCRM | C2: Pro | D2: Preço mensal | E2: R$ 249 | F2: R$ 299 | H2: Não | I2: Alto | J2: Reforçar custo-benefício em propostas
A3: 15/03/2026 | B3: MetricaPro | C3: Growth | D3: Preço mensal | E3: R$ 399 | F3: R$ 449 | G3: =IF(OR(E3="N/A",F3="N/A",NOT(ISNUMBER(SUBSTITUTE(SUBSTITUTE(E3,"R$ ",""),".","")*1))),"N/A",ROUND((VALUE(SUBSTITUTE(SUBSTITUTE(F3,"R$ ",""),".",""))-VALUE(SUBSTITUTE(SUBSTITUTE(E3,"R$ ",""),".","")))/VALUE(SUBSTITUTE(SUBSTITUTE(E3,"R$ ",""),".",""))*100,1)&"%") | H3: =IF((TODAY()-DATEVALUE(TEXT(A3,"YYYY-MM-DD")))<30,"Sim","Não") | I3: Médio | J3: Destacar preço competitivo nosso
A4: 20/03/2026 | B4: ChatBot360 | C4: Scale | D4: Feature | E4: Sem IA generativa | F4: IA generativa inclusa | G4: =ROUND((449-399)/399*100,1)&"%" | H4: =IF((TODAY()-DATEVALUE(TEXT(A4,"YYYY-MM-DD")))<30,"Sim","Não") | I4: Alto | J4: Avaliar parceria com IA ou roadmap
A5: 01/04/2026 | B5: PipeRun | C5: Avançado | D5: Preço mensal | E5: R$ 279 | F5: R$ 259 | H5: =IF((TODAY()-DATEVALUE(TEXT(A5,"YYYY-MM-DD")))<30,"Sim","Não") | I5: Alto | J5: Revisar posicionamento no tier médio
A6: 05/04/2026 | B6: NexTask | C6: Team | D6: Preço mensal | E6: R$ 179 | F6: R$ 199 | G6: =ROUND((259-279)/279*100,1)&"%" | H6: =IF((TODAY()-DATEVALUE(TEXT(A6,"YYYY-MM-DD")))<30,"Sim","Não") | I6: Baixo | J6: Sem ação necessária
A7: 10/04/2026 | B7: FlowDesk | C7: Business | D7: Usuários inclusos | E7: 3 | F7: 5 | G7: =ROUND((199-179)/179*100,1)&"%" | H7: =IF((TODAY()-DATEVALUE(TEXT(A7,"YYYY-MM-DD")))<30,"Sim","Não") | I7: Médio | J7: Considerar aumentar nosso limite
A8: 15/04/2026 | B8: RivalCRM | C8: Enterprise | D8: Novo plano | E8: N/A | F8: R$ 699 | G8: N/A | H8: =IF((TODAY()-DATEVALUE(TEXT(A8,"YYYY-MM-DD")))<30,"Sim","Não") | I8: Alto | J8: Criar oferta enterprise competitiva
A9: 22/04/2026 | B9: MetricaPro | C9: Starter | D9: Desconto anual | E9: 15% | F9: 20% | G9: N/A | H9: =IF((TODAY()-DATEVALUE(TEXT(A9,"YYYY-MM-DD")))<30,"Sim","Não") | I9: Médio | J9: Revisar nossa política de desconto anual
H10: =IF((TODAY()-DATEVALUE(TEXT(A10,"YYYY-MM-DD")))<30,"Sim","Não")

Sheet Deals
A1: Data | B1: Deal | C1: Prospect | D1: Valor (R$) | E1: Concorrente Citado | F1: Motivo Perda/Risco | G1: Receita Perdida (R$) | H1: Diferença de Preço % | I1: Status | J1: Aprendizado
A2: 02/04/2026 | B2: Deal-041 | C2: TechNova Ltda | D2: 18000 | E2: RivalCRM | F2: Preço | G2: 18000 | I2: Perdido | J2: Prospect comparou nosso Pro com Rival Pro novo a R$299
A3: 05/04/2026 | B3: Deal-042 | C3: LogiSmart | D3: 9600 | E3: PipeRun | F3: Preço | G3: =IF(I3="Perdido",D3,0) | H3: =IF(E3="","",ROUND((D3/12-VLOOKUP(E3,Concorrentes!A3:E20,5,FALSE))/VLOOKUP(E3,Concorrentes!A3:E20,5,FALSE)*100,1)&"%") | I3: Perdido | J3: PipeRun ofereceu desconto agressivo de 25%
A4: 08/04/2026 | B4: Deal-043 | C4: DataBridge | D4: 36000 | E4: MetricaPro | F4: Feature | G4: =IF(I4="Perdido",D4,0) | H4: =IF(E4="","",ROUND((D4/12-VLOOKUP(E4,Concorrentes!A3:E20,5,FALSE))/VLOOKUP(E4,Concorrentes!A3:E20,5,FALSE)*100,1)&"%") | I4: Em risco | J4: Prospect quer cohort analysis que não temos
A5: 12/04/2026 | B5: Deal-044 | C5: CloudBase | D5: 14400 | E5: FlowDesk | F5: Preço | G5: =IF(I5="Perdido",D5,0) | H5: =IF(E5="","",ROUND((D5/12-VLOOKUP(E5,Concorrentes!A3:E20,5,FALSE))/VLOOKUP(E5,Concorrentes!A3:E20,5,FALSE)*100,1)&"%") | I5: Em risco | J5: FlowDesk subiu p/ 5 usuários no Business, melhor custo/user
A6: 18/04/2026 | B6: Deal-045 | C6: RetailMax | D6: 24000 | E6: ChatBot360 | F6: Feature | G6: =IF(I6="Perdido",D6,0) | H6: =IF(E6="","",ROUND((D6/12-VLOOKUP(E6,Concorrentes!A3:E20,5,FALSE))/VLOOKUP(E6,Concorrentes!A3:E20,5,FALSE)*100,1)&"%") | I6: Em risco | J6: IA generativa do ChatBot360 impressionou o prospect
A7: 20/04/2026 | B7: Deal-046 | C7: FinControl | D7: 7200 | E7: NexTask | F7: Preço | G7: =IF(I7="Perdido",D7,0) | H7: =IF(E7="","",ROUND((D7/12-VLOOKUP(E7,Concorrentes!A3:E20,5,FALSE))/VLOOKUP(E7,Concorrentes!A3:E20,5,FALSE)*100,1)&"%") | I7: Perdido | J7: Preço similar mas NexTask tem free tier
A8: 25/04/2026 | B8: Deal-047 | C8: EduPrime | D8: 12000 | E8: RivalCRM | F8: Preço | G8: =IF(I8="Perdido",D8,0) | H8: =IF(E8="","",ROUND((D8/12-VLOOKUP(E8,Concorrentes!A3:E20,5,FALSE))/VLOOKUP(E8,Concorrentes!A3:E20,5,FALSE)*100,1)&"%") | I8: Ganho | J8: Usamos dado de aumento do Rival p/ fechar
A9: 27/04/2026 | B9: Deal-048 | C9: AgriTech | D9: 30000 | E9: MetricaPro | F9: Proposta | G9: =IF(I9="Perdido",D9,0) | H9: =IF(E9="","",ROUND((D9/12-VLOOKUP(E9,Concorrentes!A3:E20,5,FALSE))/VLOOKUP(E9,Concorrentes!A3:E20,5,FALSE)*100,1)&"%") | I9: Em negociação | J9: Prospect pediu match de preço com MetricaPro
G10: =IF(I10="Perdido",D10,0) | H10: =IF(E10="","",ROUND((D10/12-VLOOKUP(E10,Concorrentes!A3:E20,5,FALSE))/VLOOKUP(E10,Concorrentes!A3:E20,5,FALSE)*100,1)&"%")
